README.rst
setup.py
btags.egg-info/PKG-INFO
btags.egg-info/SOURCES.txt
btags.egg-info/dependency_links.txt
btags.egg-info/entry_points.txt
btags.egg-info/requires.txt
btags.egg-info/top_level.txt
btagslib/__init__.py
btagslib/version.py
btagslib/cli/__init__.py
btagslib/cli/btags.py
btagslib/db/__init__.py
btagslib/db/model.py
btagslib/db/operation.py
btagslib/debuginfo/__init__.py
btagslib/debuginfo/dwarfformat.py
btagslib/debuginfo/runner.py
btagslib/elftoolsext/__init__.py
btagslib/elftoolsext/macro.py
btagslib/tagfile/__init__.py
btagslib/tagfile/ctag.py
btagslib/terminal/__init__.py
btagslib/terminal/statusbar.py
btagslib/terminal/terminalcontroller.py