Metadata-Version: 1.2
Name: btags
Version: 0.1.1
Summary: Generate tag file according to the debug information such as DWARF including in the binary file
Home-page: https://github.com/KKRainbow/btagslib
Author: KKRainbow
Author-email: sunsijie@buaa.edu.cn
License: MIT
Keywords: dwarf ctags tag binary
Platform: Cross Platform
Classifier: Development Status :: 4 - Beta
Classifier: Intended Audience :: Developers
Classifier: Topic :: Software Development
Classifier: Programming Language :: Python :: 3
Classifier: Programming Language :: Python :: 3.3
Classifier: Programming Language :: Python :: 3.4
Classifier: Programming Language :: Python :: 3.5
Classifier: Programming Language :: Python :: 3.6
Requires-Python: >=3
